trashguy/__init__.py
trashguy/__main__.py
trashguy/_frame_engine.py
trashguy/_tgpy_engine.py
trashguy/_types.py
trashguy/generate_lut.py
trashguy/lut.py
trashguy/trashguy.py
trashguy/version.py
trashguy-4.1.0.20210114.dist-info/LICENSE
trashguy-4.1.0.20210114.dist-info/METADATA
trashguy-4.1.0.20210114.dist-info/WHEEL
trashguy-4.1.0.20210114.dist-info/top_level.txt
trashguy-4.1.0.20210114.dist-info/zip-safe
trashguy-4.1.0.20210114.dist-info/RECORD
