Metadata-Version: 2.1
Name: trashguy
Version: 4.1.0.20210114
Summary: The Original TrashGuy™ Animation!
Home-page: https://github.com/TrashGuyAnimations/TrashGuy
Author: Zac
Author-email: trashguy@zac.cy
License: AGPLv3+
Keywords: Animation,ASCII,Emoji,Fun
Platform: UNKNOWN
Classifier: Development Status :: 5 - Production/Stable
Classifier: Intended Audience :: Developers
Classifier: Topic :: Software Development :: Libraries :: Python Modules
Classifier: License :: OSI Approved :: GNU Affero General Public License v3 or later (AGPLv3+)
Classifier: Programming Language :: Python :: 3
Classifier: Programming Language :: Python :: 3.4
Classifier: Programming Language :: Python :: 3.5
Classifier: Programming Language :: Python :: 3.6
Classifier: Programming Language :: Python :: 3.7
